Metadata-Version: 2.1
Name: saysynth
Version: 1.0.8
Summary: Make music with Mac's say command
Home-page: http://saysynth.org
Author: Brian Abelson
Author-email: hey@gltd.email
License-File: LICENSE
